{
    "name": "Lemon Haze",
    "description": "Lemon Haze & Indigo Stone — electric yellow on deep navy blue.",
    "version": "1.0",
       "authors": [
        {
            "name": "Ace",
            "id": "1225921043559088138"
          }
    ],
    "semanticColors": {
        "APP_FRAME_BORDER": [ "#1a2660" ],
        "ACTION_SHEET_GRADIENT_BG": [ "#1e2d6e" ],
        "ANDROID_RIPPLE": [ "#FFEF4D30" ],
        "BACKGROUND_ACCENT": [ "#FFEF4D" ],
        "BACKGROUND_MENTIONED": [ "#FFEF4D17" ],
        "BACKGROUND_MENTIONED_HOVER": [ "#FFEF4D30" ],
        "BACKGROUND_MESSAGE_HOVER": [ "#ffffff05" ],
        "BACKGROUND_MODIFIER_ACCENT": [ "#2e3d80" ],
        "BACKGROUND_MODIFIER_ACTIVE": [ "#1a2660" ],
        "BACKGROUND_MODIFIER_HOVER": [ "#ffffff05" ],
        "BACKGROUND_MODIFIER_SELECTED": [ "#263575" ],
        "BACKGROUND_MOBILE_PRIMARY": [ "#2A428C" ],
        "BACKGROUND_MOBILE_SECONDARY": [ "#243880" ],
        "BACKGROUND_NESTED_FLOATING": [ "#2e3d80" ],
        "BACKGROUND_PRIMARY": [ "#2A428C" ],
        "BACKGROUND_SECONDARY": [ "#243880" ],
        "BACKGROUND_SECONDARY_ALT": [ "#1e2d6e" ],
        "BG_SURFACE_RAISED": [ "#1a2660" ],
        "BACKGROUND_BASE_LOW": [ "#243880" ],
        "BACKGROUND_BASE_LOWEST": [ "#1a2660" ],
        "BACKGROUND_BASE_LOWER": [ "#243880" ],
        "BORDER_FAINT": [ "#FFEF4D20" ],
        "CARD_PRIMARY_BG": [ "#2A428C" ],
        "CARD_PRIMARY_PRESSED_BG": [ "#2e3d80" ],
        "CARD_SECONDARY_BG": [ "#243880" ],
        "CHANNEL_ICON": [ "#ffe94d" ],
        "CHANNELS_DEFAULT": [ "#e8d870" ],
        "CHANNELTEXTAREA_BACKGROUND": [ "#263575" ],
        "CHAT_BACKGROUND": [ "#2A428C" ],
        "EMBED_BACKGROUND": [ "#243880" ],
        "HEADER_PRIMARY": [ "#fffacc" ],
        "HEADER_SECONDARY": [ "#fff5a0" ],
        "INPUT_BACKGROUND": [ "#1a2660" ],
        "INTERACTIVE_ACTIVE": [ "#FFEF4D" ],
        "INTERACTIVE_HOVER": [ "#ffe81a" ],
        "INTERACTIVE_MUTED": [ "#8878a0" ],
        "INTERACTIVE_NORMAL": [ "#e8d870" ],
        "TEXT_LINK": [ "#FFEF4D" ],
        "TEXT_NORMAL": [ "#f5f0cc" ],
        "TEXT_MUTED": [ "#a09860" ],
        "TEXT_PRIMARY": [ "#ede0a0" ],
        "THREAD_CHANNEL_SPINE": [ "#FFEF4D" ],
        "BG_BASE_PRIMARY": [ "#2A428C" ],
        "BG_BASE_SECONDARY": [ "#243880" ],
        "BG_BASE_TERTIARY": [ "#1a2660" ],
        "BG_MOD_FAINT": [ "#2e3d80" ],
        "BG_MOD_STRONG": [ "#223070" ],
        "BG_MOD_SUBTLE": [ "#FFEF4D15" ],
        "REDESIGN_ACTIVITY_CARD_BACKGROUND": [ "#263575" ],
        "CONTROL_CRITICAL_PRIMARY_BACKGROUND_ACTIVE": [ "#c8a800" ],
        "CONTROL_PRIMARY_BACKGROUND_DEFAULT": [ "#e8c800" ],
        "CONTROL_PRIMARY_BACKGROUND_ACTIVE": [ "#d4b400" ],
        "CONTROL_SECONDARY_BACKGROUND_DEFAULT": [ "#2e3d80" ],
        "CONTROL_SECONDARY_BACKGROUND_ACTIVE": [ "#1e2d6e" ],
        "CONTROL_SECONDARY_BORDER_DEFAULT": [ "#FFEF4D30" ],
        "CONTROL_SECONDARY_BORDER_ACTIVE": [ "#223070" ],
        "REDESIGN_BUTTON_TERTIARY_BACKGROUND": [ "#2A428C" ],
        "REDESIGN_CHANNEL_CATEGORY_NAME_TEXT": [ "#ffe94d" ],
        "REDESIGN_CHANNEL_NAME_TEXT": [ "#f5f0cc" ],
        "REDESIGN_CHAT_INPUT_BACKGROUND": [ "#263575" ],
        "MENTION_FOREGROUND": [ "#FFEF4D" ],
        "BACKGROUND_MOD_MUTED": [ "#2A428C" ],
        "STANDALONE_CHANNEL_CONTENT_BACKGROUND": [ "#2A428C" ],
        "STANDALONE_CHANNEL_HEADER_BORDER": [ "#2A428C" ],
        "INPUT_BACKGROUND_DEFAULT": [ "#1a2660" ],
        "INPUT_BORDER_ACTIVE": [ "#FFEF4D" ],
        "MOBILE_ACTIONSHEET_BACKGROUND": [ "#1e2d6e" ],
        "MOBILE_ACTIONSHEET_GRADIENT_BACKGROUND_DEFAULT": [ "#1e2d6e" ],
        "MOBILE_CHANNEL_ITEM_BACKGROUND_SELECTED": [ "#FFEF4D20" ],
        "MOBILE_SEGMENTED_CONTROL_BACKGROUND": [ "#1a2660" ],
        "PANEL_BG": [ "#2A428C" ],
        "BACKGROUND_SURFACE_HIGH": [ "#2A428C" ],
        "TAB_BAR_BACKGROUND": [ "#1e2d6e" ]
    },
    "rawColors": {
        "PRIMARY_100": "#fffacc",
        "PRIMARY_200": "#fff5a0",
        "PRIMARY_300": "#f5f0cc",
        "PRIMARY_330": "#ede0a0",
        "PRIMARY_360": "#e8d870",
        "PRIMARY_400": "#d8c860",
        "PRIMARY_460": "#2e3d80",
        "PRIMARY_500": "#7868a0",
        "PRIMARY_530": "#504880",
        "PRIMARY_600": "#2A428C",
        "PRIMARY_630": "#243880",
        "PRIMARY_645": "#1e2d6e",
        "PRIMARY_660": "#1a2660",
        "PRIMARY_700": "#2A428C",
        "PRIMARY_730": "#243880",
        "PRIMARY_800": "#141e50",
        "PLUM_10": "#9888b0",
        "PLUM_15": "#FFEF4D",
        "PLUM_16": "#1e2d6e",
        "PLUM_17": "#243880",
        "PLUM_18": "#2A428C",
        "PLUM_20": "#243880",
        "PLUM_3": "#fffacc",
        "PLUM_4": "#fff090",
        "PLUM_6": "#ffe84d",
        "BRAND_200": "#fffde0",
        "BRAND_250": "#fffbc0",
        "BRAND_260": "#fff9a0",
        "BRAND_300": "#fff780",
        "BRAND_330": "#fff560",
        "BRAND_345": "#fff340",
        "BRAND_360": "#fff130",
        "BRAND_400": "#ffef20",
        "BRAND_430": "#ffed10",
        "BRAND_500": "#FFEF4D",
        "BRAND_530": "#e8d800",
        "BRAND_560": "#d0c000",
        "BRAND_600": "#b8a800",
        "BRAND_630": "#a09000",
        "BRAND_660": "#887800",
        "BRAND_700": "#706000",
        "BRAND_730": "#584800",
        "BRAND_760": "#403400",
        "BRAND_800": "#302800",
        "BRAND_830": "#282000",
        "BRAND_860": "#201800",
        "BRAND_900": "#181000",
        "RED_100": "#fffde0",
        "RED_130": "#fffbc0",
        "RED_160": "#fff9a0",
        "RED_200": "#fff780",
        "RED_230": "#fff560",
        "RED_260": "#fff340",
        "RED_300": "#fff130",
        "RED_330": "#ffef20",
        "RED_345": "#ffed10",
        "RED_360": "#f0e000",
        "RED_400": "#e0d000",
        "RED_430": "#d0c000",
        "RED_460": "#c0b000",
        "RED_500": "#b0a000",
        "RED_530": "#a09000",
        "RED_560": "#908000",
        "RED_600": "#807000",
        "RED_630": "#706000",
        "RED_660": "#605000",
        "RED_700": "#504000",
        "RED_730": "#403000",
        "RED_760": "#302400",
        "RED_800": "#201800",
        "RED_830": "#181200",
        "RED_860": "#100c00",
        "RED_900": "#080600",
        "GREEN_100": "#fffde0",
        "GREEN_130": "#fffbc0",
        "GREEN_160": "#fff9a0",
        "GREEN_200": "#fff780",
        "GREEN_230": "#fff560",
        "GREEN_260": "#fff340",
        "GREEN_300": "#fff130",
        "GREEN_330": "#ffef20",
        "GREEN_345": "#ffed10",
        "GREEN_360": "#f0e000",
        "GREEN_400": "#e0d000",
        "GREEN_430": "#d0c000",
        "GREEN_460": "#c0b000",
        "GREEN_500": "#b0a000",
        "GREEN_530": "#a09000",
        "GREEN_560": "#908000",
        "GREEN_600": "#807000",
        "GREEN_630": "#706000",
        "GREEN_660": "#605000",
        "GREEN_700": "#504000",
        "GREEN_730": "#403000",
        "GREEN_760": "#302400",
        "GREEN_800": "#201800",
        "GREEN_830": "#181200",
        "GREEN_860": "#100c00",
        "GREEN_900": "#080600",
        "CHAT_MENTIONS_BACKGROUND_DARK": "#FFEF4D30",
        "CHAT_MENTIONS_FOREGROUND_DARK": "#FFEF4D",
        "GUILD_BOOSTING_BLUE": "#FFEF4D",
        "GUILD_BOOSTING_BLUE_FOR_GRADIENTS": "#ffe830",
        "GUILD_BOOSTING_PINK": "#ffe010",
        "GUILD_BOOSTING_PINK_REFRESH": "#ffd800",
        "GUILD_BOOSTING_PURPLE": "#ffd000",
        "GUILD_BOOSTING_PURPLE_FOR_GRADIENTS": "#ffc800",
        "ORANGE_260": "#FFEF4D",
        "ORANGE_300": "#f8e840",
        "ORANGE_330": "#f0e030",
        "ORANGE_345": "#e8d820",
        "ORANGE_360": "#e0d010",
        "ORANGE_400": "#d8c800",
        "ORANGE_430": "#d0c000",
        "ORANGE_460": "#c8b800",
        "ORANGE_500": "#c0b000",
        "ORANGE_530": "#b8a800",
        "ORANGE_560": "#b0a000",
        "ORANGE_600": "#a89800",
        "ORANGE_630": "#a09000",
        "ORANGE_660": "#988800",
        "ORANGE_700": "#908000",
        "YELLOW_260": "#FFEF4D",
        "YELLOW_300": "#f8e840",
        "YELLOW_330": "#f0e030",
        "YELLOW_345": "#e8d820",
        "YELLOW_360": "#e0d010",
        "YELLOW_400": "#d8c800",
        "YELLOW_430": "#d0c000",
        "YELLOW_460": "#c8b800",
        "YELLOW_500": "#c0b000",
        "YELLOW_530": "#b8a800",
        "YELLOW_560": "#b0a000",
        "YELLOW_600": "#a89800",
        "YELLOW_630": "#a09000",
        "YELLOW_660": "#988800",
        "YELLOW_700": "#908000",
        "BLUE_260": "#FFEF4D",
        "BLUE_300": "#f8e840",
        "BLUE_330": "#f0e030",
        "BLUE_345": "#e8d820",
        "BLUE_360": "#e0d010",
        "BLUE_400": "#d8c800",
        "BLUE_430": "#d0c000",
        "BLUE_460": "#c8b800",
        "BLUE_500": "#c0b000",
        "BLUE_530": "#b8a800",
        "BLUE_560": "#b0a000",
        "BLUE_600": "#a89800",
        "BLUE_630": "#a09000",
        "BLUE_660": "#988800",
        "BLUE_700": "#908000",
        "WHITE_500": "#f5f0cc",
        "BLACK_500": "#f5f0cc",
        "WHITE_630": "#786840"
    },
    "background": {
        "blur": 0.1,
        "url": "https://raw.githubusercontent.com/Tachyon-os/Tachy_Themes/main/lemon-haze-wallpaper.png"
    },
    "plus": {
        "version": "0",
        "iconpack": "solarduotone",
        "mentionLineColor": "#FFEF4D",
        "customOverlays": true,
        "icons": {
            "ic_radio_circle_checked": "#FFEF4D",
            "ic_radio_circle_checked__overlay": "#2A428C",
            "ic_radio_square_24px": "#FFEF4D",
            "ic_radio_square_checked_24px": "#FFEF4D",
            "ic_radio_square_checked_24px__overlay": "#2A428C",
            "ic_rich_presence_dark_12px": "#a09860",
            "ic_selection_checked_24px": "#FFEF4D",
            "ic_selection_checked_24px__overlay": "#2A428C",
            "ic_star_filled": "#FFEF4D",
            "img_guild_folder": "#FFEF4D",
            "StatusMobileOnline": "#FFEF4D",
            "StatusOnline": "#FFEF4D",
            "StatusIdle": "#e8d870",
            "StatusDND": "#ffe000",
            "StatusOffline": "#786840",
            "ic_mic": "#FFEF4D",
            "ic_mic_muted": "#a09860",
            "ic_headset": "#FFEF4D",
            "ic_deafen": "#a09860",
            "ic_call_incoming": "#FFEF4D",
            "ic_call_outgoing": "#FFEF4D",
            "ic_call_missed": "#ffe000",
            "ic_add_friend": "#FFEF4D",
            "ic_mention": "#FFEF4D",
            "ic_reply": "#e8d870",
            "ic_thread": "#FFEF4D",
            "ic_pin": "#e8d870",
            "ic_emoji": "#FFEF4D",
            "ic_gift": "#FFEF4D",
            "ic_plus_circle": "#FFEF4D",
            "ic_search": "#e8d870",
            "ic_settings": "#e8d870",
            "ic_home": "#FFEF4D",
            "ic_friends": "#FFEF4D",
            "ic_nitro": "#FFEF4D",
            "ic_message": "#FFEF4D",
            "ic_bell": "#FFEF4D",
            "ic_bell_slash": "#a09860"
        }
    },
    "spec": 2
}
